Metadata-Version: 2.1
Name: Mensajes-cammil
Version: 7.0
Summary: Un paquete para saludar y despedir
Home-page: https://www.hektor.dev
Author: camila viloria
Author-email: camilaviloria37@gmail.com
Classifier: Environment :: Console
Classifier: Intended Audience :: Developers
Classifier: License :: OSI Approved :: MIT License
Classifier: Operating System :: OS Independent
Classifier: Programming Language :: Python
Classifier: Programming Language :: Python :: 3.9
Classifier: Programming Language :: Python :: 3.10
Classifier: Topic :: Utilities
License-File: LICENSE
Requires-Dist: numpy >=1.23.0
